lift_utils/__init__.py
lift_utils/base.py
lift_utils/config.py
lift_utils/datatypes.py
lift_utils/errors.py
lift_utils/header.py
lift_utils/lexicon.py
lift_utils/utils.py
lift_utils-0.3.dist-info/LICENSE
lift_utils-0.3.dist-info/METADATA
lift_utils-0.3.dist-info/WHEEL
lift_utils-0.3.dist-info/top_level.txt
lift_utils-0.3.dist-info/RECORD
