Metadata-Version: 2.1
Name: lift_utils
Version: 0.3
Summary: Read and write LIFT files in Python.
Author-email: Nate Marti <nate_marti@sil.org>
License: MIT License
Project-URL: Documentation, https://sil-car.github.io/lift-utils
Project-URL: Homepage, https://sil-car.github.io/lift-utils
Project-URL: Issues, https://github.com/sil-car/lift-utils/issues
Project-URL: Source, https://github.com/sil-car/lift-utils
Classifier: Programming Language :: Python :: 3
Classifier: License :: OSI Approved :: MIT License
Classifier: Operating System :: OS Independent
Classifier: Development Status :: 4 - Beta
Classifier: Environment :: Console
Classifier: Topic :: Text Processing :: Markup :: XML
Requires-Python: >=3.8
License-File: LICENSE
Requires-Dist: lxml >=5.2.1
Requires-Dist: Unidecode >=1.3.8
